agent/__init__.py
agent/services/__init__.py
agent/services/processUserQuery.py
agent/template/__init__.py
agent/template/agentTemplate.py
agent/template/toolsTemplate.py
agent/tools/__init__.py
agent/tools/tools.py
cli/__init__.py
cli/main.py
cli/ApiUtil/UserService.py
cli/ApiUtil/__init__.py
cli/session/SessionManager.py
cli/session/__init__.py
constants/__init__.py
constants/constants.py
github_chatbot-1.0.4.dist-info/licenses/LICENSE
github_chatbot-1.0.4.dist-info/METADATA
github_chatbot-1.0.4.dist-info/WHEEL
github_chatbot-1.0.4.dist-info/entry_points.txt
github_chatbot-1.0.4.dist-info/top_level.txt
github_chatbot-1.0.4.dist-info/RECORD
