Metadata-Version: 2.4
Name: github-chatbot
Version: 1.0.4
License-File: LICENSE
Requires-Dist: click
Requires-Dist: requests
Requires-Dist: python-dotenv
Requires-Dist: rich
Requires-Dist: openai
Requires-Dist: cryptography
Dynamic: license-file
Dynamic: requires-dist
